LICENSE
README.md
requirements.txt
setup.py
shangqi_cloud_lib/__init__.py
shangqi_cloud_lib/context.py
shangqi_cloud_lib/router.py
shangqi_cloud_lib/server.py
shangqi_cloud_lib.egg-info/PKG-INFO
shangqi_cloud_lib.egg-info/SOURCES.txt
shangqi_cloud_lib.egg-info/dependency_links.txt
shangqi_cloud_lib.egg-info/requires.txt
shangqi_cloud_lib.egg-info/top_level.txt
shangqi_cloud_lib/frame/BaseHandler.py
shangqi_cloud_lib/frame/DocHandler.py
shangqi_cloud_lib/frame/HandlerHelper.py
shangqi_cloud_lib/frame/__init__.py
shangqi_cloud_lib/templates/doc.html
shangqi_cloud_lib/templates/record.html
shangqi_cloud_lib/utils/AesUtil.py
shangqi_cloud_lib/utils/BusinessUtil.py
shangqi_cloud_lib/utils/CacheUtil.py
shangqi_cloud_lib/utils/CommonUtil.py
shangqi_cloud_lib/utils/CustomException.py
shangqi_cloud_lib/utils/DBUtil.py
shangqi_cloud_lib/utils/DataClient.py
shangqi_cloud_lib/utils/DateUtil.py
shangqi_cloud_lib/utils/ElasticsearchUtil.py
shangqi_cloud_lib/utils/FileUtil.py
shangqi_cloud_lib/utils/HttpUtil.py
shangqi_cloud_lib/utils/IOUtil.py
shangqi_cloud_lib/utils/JwtUtil.py
shangqi_cloud_lib/utils/MongodbUtil.py
shangqi_cloud_lib/utils/MysqlUtil.py
shangqi_cloud_lib/utils/RSAUtil.py
shangqi_cloud_lib/utils/SqlAlchemy.py
shangqi_cloud_lib/utils/SqlFormatUtil.py
shangqi_cloud_lib/utils/ThreadUtil.py
shangqi_cloud_lib/utils/__init__.py